[{"name": "benchmarks.BasicPhysipy.mem_unit", "idx": null, "pretty_name": "benchmarks.BasicPhysipy.mem_unit", "last_rev": null, "last_value": null, "last_err": null, "prev_value": null, "change_rev": null}, {"name": "benchmarks.BasicPhysipy.time_QuantityAdd", "idx": null, "pretty_name": "benchmarks.BasicPhysipy.time_QuantityAdd", "last_rev": 920, "last_value": 1.847104543112943e-06, "last_err": 1.2219114720365645e-08, "prev_value": null, "change_rev": null}, {"name": "benchmarks.BasicPhysipy.time_QuantityCreation", "idx": null, "pretty_name": "benchmarks.BasicPhysipy.time_QuantityCreation", "last_rev": 920, "last_value": 1.9135087789738506e-06, "last_err": 2.1970764332509758e-08, "prev_value": null, "change_rev": null}, {"name": "benchmarks.BasicPhysipy.time_QuantityCreationByArray", "idx": null, "pretty_name": "benchmarks.BasicPhysipy.time_QuantityCreationByArray", "last_rev": 920, "last_value": 9.933692016356461e-06, "last_err": 2.2265888335283648e-07, "prev_value": null, "change_rev": null}, {"name": "benchmarks.BasicPhysipy.time_QuantityCreationByExpr", "idx": null, "pretty_name": "benchmarks.BasicPhysipy.time_QuantityCreationByExpr", "last_rev": 920, "last_value": 0.00019056592378238182, "last_err": 1.9198943189252687e-06, "prev_value": null, "change_rev": null}, {"name": "benchmarks.BasicPhysipy.time_QuantityCreationByMul", "idx": null, "pretty_name": "benchmarks.BasicPhysipy.time_QuantityCreationByMul", "last_rev": 920, "last_value": 7.436056666147824e-06, "last_err": 8.857838395218661e-08, "prev_value": null, "change_rev": null}, {"name": "benchmarks.BasicPhysipy.time_arr_scalar_op_add", "idx": null, "pretty_name": "benchmarks.BasicPhysipy.time_arr_scalar_op_add", "last_rev": 920, "last_value": 3.800356857640532e-06, "last_err": 5.578169431195404e-08, "prev_value": null, "change_rev": null}, {"name": "benchmarks.BasicPhysipy.time_arr_scalar_op_div", "idx": null, "pretty_name": "benchmarks.BasicPhysipy.time_arr_scalar_op_div", "last_rev": 920, "last_value": 8.738230604078036e-06, "last_err": 2.2507399926577675e-07, "prev_value": null, "change_rev": null}, {"name": "benchmarks.BasicPhysipy.time_arr_scalar_op_mul", "idx": null, "pretty_name": "benchmarks.BasicPhysipy.time_arr_scalar_op_mul", "last_rev": 920, "last_value": 8.275975784691661e-06, "last_err": 2.2051572640159473e-07, "prev_value": null, "change_rev": null}, {"name": "benchmarks.BasicPhysipy.time_arr_scalar_op_pow", "idx": null, "pretty_name": "benchmarks.BasicPhysipy.time_arr_scalar_op_pow", "last_rev": 920, "last_value": 6.493868541398088e-06, "last_err": 9.904126102526709e-08, "prev_value": null, "change_rev": null}, {"name": "benchmarks.BasicPhysipy.time_arr_scalar_op_sub", "idx": null, "pretty_name": "benchmarks.BasicPhysipy.time_arr_scalar_op_sub", "last_rev": 920, "last_value": 3.8090337892952976e-06, "last_err": 1.0341774029023783e-07, "prev_value": null, "change_rev": null}, {"name": "benchmarks.BasicPhysipy.time_arr_scalar_op_truediv", "idx": null, "pretty_name": "benchmarks.BasicPhysipy.time_arr_scalar_op_truediv", "last_rev": 920, "last_value": 5.8790388998248395e-06, "last_err": 6.27064012291074e-08, "prev_value": null, "change_rev": null}, {"name": "benchmarks.BasicPhysipy.time_scalar_op_add", "idx": null, "pretty_name": "benchmarks.BasicPhysipy.time_scalar_op_add", "last_rev": 920, "last_value": 1.8390874333253677e-06, "last_err": 2.8867290607568848e-08, "prev_value": null, "change_rev": null}, {"name": "benchmarks.BasicPhysipy.time_scalar_op_div", "idx": null, "pretty_name": "benchmarks.BasicPhysipy.time_scalar_op_div", "last_rev": 920, "last_value": 5.83999494489889e-06, "last_err": 7.868058093536121e-08, "prev_value": null, "change_rev": null}, {"name": "benchmarks.BasicPhysipy.time_scalar_op_mul", "idx": null, "pretty_name": "benchmarks.BasicPhysipy.time_scalar_op_mul", "last_rev": 920, "last_value": 5.45264810427779e-06, "last_err": 6.99449104712138e-08, "prev_value": null, "change_rev": null}, {"name": "benchmarks.BasicPhysipy.time_scalar_op_pow", "idx": null, "pretty_name": "benchmarks.BasicPhysipy.time_scalar_op_pow", "last_rev": 920, "last_value": 5.659399083223128e-06, "last_err": 6.309305439954633e-08, "prev_value": null, "change_rev": null}, {"name": "benchmarks.BasicPhysipy.time_scalar_op_sub", "idx": null, "pretty_name": "benchmarks.BasicPhysipy.time_scalar_op_sub", "last_rev": 920, "last_value": 1.8304616368664794e-06, "last_err": 2.4537519435628006e-08, "prev_value": null, "change_rev": null}, {"name": "benchmarks.BasicPhysipy.time_scalar_op_truediv", "idx": null, "pretty_name": "benchmarks.BasicPhysipy.time_scalar_op_truediv", "last_rev": 920, "last_value": 2.4130110683269987e-06, "last_err": 0.0, "prev_value": 2.294126025558603e-06, "change_rev": [846, 920]}, {"name": "benchmarks.BasicPhysipy.time_use_case", "idx": null, "pretty_name": "benchmarks.BasicPhysipy.time_use_case", "last_rev": 920, "last_value": 0.00010913116663383941, "last_err": 1.6780177163709326e-06, "prev_value": null, "change_rev": null}, {"name": "benchmarks.BasicPhysipy.time_use_case2", "idx": null, "pretty_name": "benchmarks.BasicPhysipy.time_use_case2", "last_rev": 920, "last_value": 0.00015772295716617787, "last_err": 7.151300138221153e-07, "prev_value": 0.00015523953709017599, "change_rev": [null, 839]}, {"name": "benchmarks.BenchDimension.time_dimension_div", "idx": null, "pretty_name": "benchmarks.BenchDimension.time_dimension_div", "last_rev": 920, "last_value": 2.9619743843761453e-06, "last_err": 1.7718614179855734e-08, "prev_value": null, "change_rev": null}, {"name": "benchmarks.BenchDimension.time_dimension_eq", "idx": null, "pretty_name": "benchmarks.BenchDimension.time_dimension_eq", "last_rev": 920, "last_value": 3.08427128341826e-07, "last_err": 7.012283416770634e-09, "prev_value": null, "change_rev": null}, {"name": "benchmarks.BenchDimension.time_dimension_mul", "idx": null, "pretty_name": "benchmarks.BenchDimension.time_dimension_mul", "last_rev": 920, "last_value": 2.9850710780409895e-06, "last_err": 1.887429403475624e-08, "prev_value": null, "change_rev": null}, {"name": "benchmarks.BenchDimension.time_dimension_pow", "idx": null, "pretty_name": "benchmarks.BenchDimension.time_dimension_pow", "last_rev": 920, "last_value": 3.0107903463185534e-06, "last_err": 1.9023837988923813e-08, "prev_value": null, "change_rev": null}, {"name": "benchmarks.TimeSuite.time_range", "idx": null, "pretty_name": "benchmarks.TimeSuite.time_range", "last_rev": 920, "last_value": 2.400787475350119e-05, "last_err": 3.0150969909307243e-07, "prev_value": null, "change_rev": null}, {"name": "imports.timeraw_import_constants", "idx": null, "pretty_name": "imports.timeraw_import_constants", "last_rev": 920, "last_value": 0.4494503255118616, "last_err": 0.0, "prev_value": 0.5916435139370151, "change_rev": [846, 920]}, {"name": "imports.timeraw_import_customunits", "idx": null, "pretty_name": "imports.timeraw_import_customunits", "last_rev": 846, "last_value": 0.5927119259722531, "last_err": 0.0016552265818130945, "prev_value": null, "change_rev": null}, {"name": "imports.timeraw_import_math", "idx": null, "pretty_name": "imports.timeraw_import_math", "last_rev": 920, "last_value": 0.45252739399438724, "last_err": 0.0, "prev_value": 0.5946138795115985, "change_rev": [846, 920]}, {"name": "imports.timeraw_import_physipy", "idx": null, "pretty_name": "imports.timeraw_import_physipy", "last_rev": 920, "last_value": 0.4497394789941609, "last_err": 0.0, "prev_value": 0.5934830849873833, "change_rev": [846, 920]}, {"name": "imports.timeraw_import_physipy_calculus", "idx": null, "pretty_name": "imports.timeraw_import_physipy_calculus", "last_rev": 846, "last_value": 0.5937150344834663, "last_err": 0.00487701535602344, "prev_value": null, "change_rev": null}, {"name": "imports.timeraw_import_physipy_dimension", "idx": null, "pretty_name": "imports.timeraw_import_physipy_dimension", "last_rev": 920, "last_value": 0.45272126147756353, "last_err": 0.0, "prev_value": 0.5927235330455005, "change_rev": [846, 920]}, {"name": "imports.timeraw_import_physipy_plot", "idx": null, "pretty_name": "imports.timeraw_import_physipy_plot", "last_rev": 846, "last_value": 0.5945951514877379, "last_err": 0.004516160847326637, "prev_value": null, "change_rev": null}, {"name": "imports.timeraw_import_physipy_quantity", "idx": null, "pretty_name": "imports.timeraw_import_physipy_quantity", "last_rev": 920, "last_value": 0.44811701198341325, "last_err": 0.0, "prev_value": 0.5921154840034433, "change_rev": [846, 920]}, {"name": "imports.timeraw_import_physipy_units", "idx": null, "pretty_name": "imports.timeraw_import_physipy_units", "last_rev": 920, "last_value": 0.45014807098777965, "last_err": 0.0, "prev_value": 0.5946716770413332, "change_rev": [846, 920]}, {"name": "imports.timeraw_import_random", "idx": null, "pretty_name": "imports.timeraw_import_random", "last_rev": 846, "last_value": 0.59069066750817, "last_err": 0.0028710752993819913, "prev_value": null, "change_rev": null}, {"name": "imports.timeraw_import_units", "idx": null, "pretty_name": "imports.timeraw_import_units", "last_rev": 920, "last_value": 0.4515703624347225, "last_err": 0.0, "prev_value": 0.5929898869944736, "change_rev": [846, 920]}]